safe_s1/__init__.py
safe_s1/config.yml
safe_s1/getconfig.py
safe_s1/reader.py
safe_s1/sentinel1_xml_mappings.py
safe_s1/xml_parser.py
xarray_safe_s1-2026.1.23.dist-info/licenses/LICENSE
xarray_safe_s1-2026.1.23.dist-info/METADATA
xarray_safe_s1-2026.1.23.dist-info/WHEEL
xarray_safe_s1-2026.1.23.dist-info/top_level.txt
xarray_safe_s1-2026.1.23.dist-info/RECORD
