Metadata-Version: 2.4
Name: xarray-safe-s1
Version: 2026.1.23
License: MIT
Requires-Python: >=3.9
License-File: LICENSE
Requires-Dist: geopandas
Requires-Dist: numpy
Requires-Dist: xarray>=2024.10.0
Requires-Dist: lxml
Requires-Dist: rioxarray
Requires-Dist: jmespath
Requires-Dist: fsspec
Requires-Dist: rasterio
Requires-Dist: affine
Requires-Dist: pandas
Requires-Dist: shapely
Requires-Dist: pyproj
Requires-Dist: dask
Requires-Dist: aiohttp
Dynamic: license-file
